{
    "rooms": [
      {
        "id": "1-82",
        "coords": [
          { "x": 0, "y": 0 },
          { "x": 2000, "y": 0 },
          { "x": 2000, "y": 8000 },
          { "x": 0, "y": 8000 }
        ]
      },
      {
        "id": "1-75",
        "coords": [
          { "x": 2000, "y": 0 },
          { "x": 7000, "y": 0 },
          { "x": 7000, "y": 8500 },
          { "x": 2000, "y": 8500 }
        ]
      },
      {
        "id": "1-74A",
        "coords": [
          { "x": 6400, "y": 0 },
          { "x": 7000, "y": 0 },
          { "x": 7000, "y": 2000 },
          { "x": 6400, "y": 2000 }
        ]
      },
      {
        "id": "1-76A",
        "coords": [
          { "x": 6400, "y": 2000 },
          { "x": 7000, "y": 2000 },
          { "x": 7000, "y": 4000 },
          { "x": 6400, "y": 4000 }
        ]
      },
      {
        "id": "1-74B",
        "coords": [
          { "x": 7000, "y": 0 },
          { "x": 7600, "y": 0 },
          { "x": 7600, "y": 2000 },
          { "x": 7000, "y": 2000 }
        ]
      },
      {
        "id": "1-76B",
        "coords": [
          { "x": 7000, "y": 2000 },
          { "x": 7600, "y": 2000 },
          { "x": 7600, "y": 4000 },
          { "x": 7000, "y": 4000 }
        ]
      }
    ]
  }
  